Metadata-Version: 1.2
Name: ChangeTrade
Version: 1.0.2
Summary: My usefull functions trading Binance ---processe data --- Tensorflow Model Deep BLSTM BGRU WAVENET5 CNN 
Home-page: https://None.come
Author: Charles Hajjar
License: WTFPL
Platform: UNKNOWN
Requires-Python: >=3.9
